openstereo/__init__.py
openstereo/__main__.py
openstereo/data_models.py
openstereo/io.py
openstereo/ndtri_back.py
openstereo/os_auttitude.py
openstereo/os_base.py
openstereo/os_math.py
openstereo/os_plot.py
openstereo/plot_data.py
openstereo/projection_models.py
openstereo/tools/__init__.py
openstereo/tools/mesh_process.py
openstereo/ui/__init__.py
openstereo/ui/circular_properties_ui.py
openstereo/ui/clipboard_ui.py
openstereo/ui/difference_vectors_ui.py
openstereo/ui/fault_data_ui.py
openstereo/ui/fault_properties_ui.py
openstereo/ui/import_dialog_ui.py
openstereo/ui/import_ply_ui.py
openstereo/ui/item_table_ui.py
openstereo/ui/languages.py
openstereo/ui/line_properties_ui.py
openstereo/ui/merge_data_ui.py
openstereo/ui/openstereo_rc.py
openstereo/ui/openstereo_ui.py
openstereo/ui/os_settings_ui.py
openstereo/ui/plane_properties_ui.py
openstereo/ui/rotate_data_ui.py
openstereo/ui/singleline_properties_ui.py
openstereo/ui/singleplane_properties_ui.py
openstereo/ui/singlesmallcircle_properties_ui.py
openstereo/ui/slope_properties_ui.py
openstereo/ui/smallcircle_properties_ui.py
openstereo/ui/ui_interface.py
OpenStereo-2.0b12.dist-info/LICENSE
OpenStereo-2.0b12.dist-info/METADATA
OpenStereo-2.0b12.dist-info/WHEEL
OpenStereo-2.0b12.dist-info/entry_points.txt
OpenStereo-2.0b12.dist-info/top_level.txt
OpenStereo-2.0b12.dist-info/RECORD
