Metadata-Version: 2.1
Name: OpenStereo
Version: 2.0b12
Summary: Software for analysis of structural data
Home-page: https://github.com/spamlab-iee/os
Author: Arthur Endlein
Author-email: endarthur@gmail.com
License: GPLv3
Download-URL: https://github.com/spamlab-iee/os/archive/v0.9.0.tar.gz
Keywords: geology attitude stereonet projection structural
Platform: UNKNOWN
Classifier: Development Status :: 3 - Alpha
Classifier: Topic :: Scientific/Engineering
Classifier: License :: OSI Approved :: GNU General Public License v3 (GPLv3)
Requires-Dist: numpy
Requires-Dist: matplotlib
Requires-Dist: appdirs
Requires-Dist: PyQt5
Requires-Dist: xlrd
Requires-Dist: PyShp
Requires-Dist: networkx
Requires-Dist: ply2atti
Requires-Dist: auttitude (==0.1.4)
Requires-Dist: chardet
